[
  {
    "balance_func": [
      "balanceOf(address)",
      [
        {
          "address": "$userAddress"
        }
      ],
      [
        "uint256"
      ],
      "0x4da9b813057d04baef4e5800e36083717b4a0341"
    ],
    "decimals": 18,
    "modifiers": [],
    "name": "aTUSD",
    "parent_asset": "TUSD",
    "type": "lent",
    "value_index": 0,
    "protocol": "Aave"
  },
  {
    "balance_func": [
      "getUserReserveData(address,address)",
      [
        {
          "address": "0x0000000000085d4780B73119b644AE5ecd22b376"
        },
        {
          "address": "$userAddress"
        }
      ],
      [
        "uint256",
        "uint256"
      ],
      "0x398eC7346DcD622eDc5ae82352F02bE94C62d119"
    ],
    "decimals": 18,
    "modifiers": [],
    "name": "Aave Borrowed TUSD",
    "parent_asset": "TUSD",
    "type": "borrowed",
    "value_index": 1,
    "protocol": "Aave"
  },
  {
    "balance_func": [
      "balanceOf(address)",
      [
        {
          "address": "$userAddress"
        }
      ],
      [
        "uint256"
      ],
      "0x101cc05f4a51c0319f570d5e146a8c625198e636"
    ],
    "decimals": 18,
    "modifiers": [],
    "name": "aTUSD V2",
    "parent_asset": "TUSD",
    "type": "lent",
    "value_index": 0,
    "protocol": "Aave"
  },
  {
    "balance_func": [
      "balanceOf(address)",
      [
        {
          "address": "$userAddress"
        }
      ],
      [
        "uint256"
      ],
      "0x7f38d60D94652072b2C44a18c0e14A481EC3C0dd"
    ],
    "decimals": 18,
    "modifiers": [],
    "name": "Stable Rate Aave V2 Borrowed TUSD",
    "parent_asset": "TUSD",
    "type": "borrowed",
    "value_index": 0,
    "protocol": "Aave"
  },
  {
    "balance_func": [
      "balanceOf(address)",
      [
        {
          "address": "$userAddress"
        }
      ],
      [
        "uint256"
      ],
      "0x01C0eb1f8c6F1C1bF74ae028697ce7AA2a8b0E92"
    ],
    "decimals": 18,
    "modifiers": [],
    "name": "Variable Rate Aave V2 Borrowed TUSD",
    "parent_asset": "TUSD",
    "type": "borrowed",
    "value_index": 0,
    "protocol": "Aave"
  }
]